AUTHORS.rst
COPYING
README.rst
setup.py
cockpit/__init__.py
cockpit/__main__.py
cockpit/config.py
cockpit/depot.py
cockpit/events.py
cockpit/status.py
cockpit/devices/__init__.py
cockpit/devices/aerotechAxis.py
cockpit/devices/aurox.py
cockpit/devices/boulderSLM.py
cockpit/devices/camera.py
cockpit/devices/device.py
cockpit/devices/drawer.py
cockpit/devices/dummies.py
cockpit/devices/dummyAnalog.py
cockpit/devices/executorDevices.py
cockpit/devices/light.py
cockpit/devices/linkamStage.py
cockpit/devices/microscopeCamera.py
cockpit/devices/microscopeDevice.py
cockpit/devices/nanomover.py
cockpit/devices/ni_cRIOFPGA.py
cockpit/devices/objective.py
cockpit/devices/physikInstrumenteM687.py
cockpit/devices/picomotor.py
cockpit/devices/polarizationRotator.py
cockpit/devices/server.py
cockpit/devices/shutter.py
cockpit/devices/sr470.py
cockpit/devices/stage.py
cockpit/experiment/SIMFlux.py
cockpit/experiment/__init__.py
cockpit/experiment/actionTable.py
cockpit/experiment/dataSaver.py
cockpit/experiment/experiment.py
cockpit/experiment/experimentRegistry.py
cockpit/experiment/immediateMode.py
cockpit/experiment/offsetGainCorrection.py
cockpit/experiment/optoScriptExample.py
cockpit/experiment/responseMap.py
cockpit/experiment/rotatorSweep.py
cockpit/experiment/si2d.py
cockpit/experiment/structuredIllumination.py
cockpit/experiment/stutteredZStack.py
cockpit/experiment/sweptShutter.py
cockpit/experiment/zStack.py
cockpit/gui/__init__.py
cockpit/gui/device.py
cockpit/gui/fileViewerWindow.py
cockpit/gui/freetype.py
cockpit/gui/guiUtils.py
cockpit/gui/imageSequenceViewer.py
cockpit/gui/joystick.py
cockpit/gui/keyboard.py
cockpit/gui/loggingWindow.py
cockpit/gui/mainPanels.py
cockpit/gui/mainWindow.py
cockpit/gui/primitive.py
cockpit/gui/progressDialog.py
cockpit/gui/safeControls.py
cockpit/gui/shellWindow.py
cockpit/gui/touchscreen.py
cockpit/gui/viewFileDropTarget.py
cockpit/gui/camera/__init__.py
cockpit/gui/camera/viewPanel.py
cockpit/gui/camera/window.py
microscope_cockpit.egg-info/PKG-INFO
microscope_cockpit.egg-info/SOURCES.txt
microscope_cockpit.egg-info/dependency_links.txt
microscope_cockpit.egg-info/entry_points.txt
microscope_cockpit.egg-info/requires.txt
microscope_cockpit.egg-info/top_level.txt