Metadata-Version: 2.1
Name: microscope-cockpit
Version: 2.9.2
Summary: Hardware agnostic microscope user interface
Home-page: https://github.com/microscope-cockpit/cockpit
Author: See source for a complete list of contributors
Author-email:  
License: GPL-3.0+
Classifier: Intended Audience :: Science/Research
Classifier: Topic :: Scientific/Engineering
Classifier: License :: OSI Approved :: GNU General Public License v3 or later (GPLv3+)
Requires-Python: >=3.5
License-File: COPYING
License-File: AUTHORS.rst
